lmquant/__init__.py
lmquant/dataset/__init__.py
lmquant/dataset/cache/__init__.py
lmquant/dataset/cache/action.py
lmquant/dataset/cache/activation.py
lmquant/dataset/cache/calibration.py
lmquant/dataset/config.py
lmquant/dataset/transform.py
lmquant/eval/__init__.py
lmquant/eval/config.py
lmquant/llm/__init__.py
lmquant/llm/config.py
lmquant/llm/dataset.py
lmquant/llm/eval.py
lmquant/llm/model.py
lmquant/llm/nn/__init__.py
lmquant/llm/nn/attention.py
lmquant/llm/nn/struct.py
lmquant/llm/quant/__init__.py
lmquant/llm/quant/activation.py
lmquant/llm/quant/bias.py
lmquant/llm/quant/config.py
lmquant/llm/quant/reorder.py
lmquant/llm/quant/rotate.py
lmquant/llm/quant/smooth.py
lmquant/llm/quant/weight.py
lmquant/llm/run.py
lmquant/llm/utils.py
lmquant/model/__init__.py
lmquant/model/config.py
lmquant/nn/__init__.py
lmquant/quant/__init__.py
lmquant/quant/calib/__init__.py
lmquant/quant/calib/bias.py
lmquant/quant/calib/calibrator/base/__init__.py
lmquant/quant/calib/calibrator/base/search.py
lmquant/quant/calib/calibrator/range.py
lmquant/quant/calib/calibrator/reorder.py
lmquant/quant/calib/calibrator/smooth.py
lmquant/quant/calib/config/__init__.py
lmquant/quant/calib/config/base/__init__.py
lmquant/quant/calib/config/base/common.py
lmquant/quant/calib/config/base/search.py
lmquant/quant/calib/config/range.py
lmquant/quant/calib/config/reorder.py
lmquant/quant/calib/config/rotation.py
lmquant/quant/calib/config/smooth.py
lmquant/quant/calib/rotate.py
lmquant/quant/calib/smooth.py
lmquant/quant/config/__init__.py
lmquant/quant/config/model.py
lmquant/quant/config/module.py
lmquant/quant/data/__init__.py
lmquant/quant/data/codebook.py
lmquant/quant/data/dtype.py
lmquant/quant/data/metric.py
lmquant/quant/data/range.py
lmquant/quant/data/scale.py
lmquant/quant/data/tensor.py
lmquant/quant/data/utils/__init__.py
lmquant/quant/data/utils/dtype.py
lmquant/quant/data/utils/scale.py
lmquant/quant/data/utils/shape.py
lmquant/quant/functional/__init__.py
lmquant-0.0.0.dist-info/LICENSE
lmquant-0.0.0.dist-info/METADATA
lmquant-0.0.0.dist-info/WHEEL
lmquant-0.0.0.dist-info/RECORD
