Metadata-Version: 2.1
Name: lmquant
Version: 0.0.0
Summary: This package is used for evaluating large foundation models quantization in deep learning.
License: Apache-2.0
Author: Yujun Lin
Requires-Python: >=3.10,<3.12
Classifier: License :: OSI Approved :: Apache Software License
Classifier: Programming Language :: Python :: 3
Classifier: Programming Language :: Python :: 3.10
Classifier: Programming Language :: Python :: 3.11
Requires-Dist: accelerate (>=0.26.0)
Requires-Dist: bitsandbytes (>=0.42.0)
Requires-Dist: datasets (>=2.16.0)
Requires-Dist: lm_eval (>=0.4.2)
Requires-Dist: ninja (>=1.11.1)
Requires-Dist: omniconfig (>=0.1.5)
Requires-Dist: protobuf (>=5.26.0)
Requires-Dist: sentencepiece (>=0.1.99)
Requires-Dist: torch (>=2.2.0)
Requires-Dist: tqdm (>=4.66.0)
Requires-Dist: transformers (>=4.37.0)
